stockdex/__init__.py
stockdex/config.py
stockdex/digrin_interface.py
stockdex/exceptions.py
stockdex/finviz_interface.py
stockdex/justetf_interface.py
stockdex/lib.py
stockdex/macrotrends_interface.py
stockdex/nasdaq_interface.py
stockdex/sankey_charts.py
stockdex/selenium_interface.py
stockdex/ticker.py
stockdex/ticker_base.py
stockdex/yahoo_api_interface.py
stockdex/yahoo_web_interface.py
stockdex/chromedriver_linux64/LICENSE.chromedriver
stockdex/chromedriver_linux64/chromedriver
stockdex-1.2.4.dist-info/licenses/LICENSE
tests/__init__.py
tests/test_digrin_interface.py
tests/test_finviz_interface.py
tests/test_justetf_interface.py
tests/test_lib.py
tests/test_macrotrends_interface.py
tests/test_nasdaq_interface.py
tests/test_sankey_charts.py
tests/test_ticker.py
tests/test_yahoo_api_interface.py
tests/test_yahoo_web_interface.py
stockdex-1.2.4.dist-info/METADATA
stockdex-1.2.4.dist-info/WHEEL
stockdex-1.2.4.dist-info/top_level.txt
stockdex-1.2.4.dist-info/RECORD
