Metadata-Version: 2.4
Name: stockdex
Version: 1.2.4
Summary: A package to get stock data from Yahoo Finance
Home-page: https://github.com/ahnazary/stockdex
Author: Amir Nazary
Author-email: ah.nazary.aghchemazary@gmail.com
Classifier: Programming Language :: Python :: 3
Classifier: License :: OSI Approved :: MIT License
Classifier: Operating System :: OS Independent
Requires-Python: >=3.8
License-File: LICENSE
Requires-Dist: beautifulsoup4==4.12.3
Requires-Dist: numpy
Requires-Dist: pandas>=2.2.3
Requires-Dist: plotly>=5.24.1
Requires-Dist: selenium==4.25.0
Requires-Dist: plotly>=5.24.1
Requires-Dist: dash>=2.18.0
Requires-Dist: curl_cffi==0.12.0
Requires-Dist: lxml>=5.3.0
Dynamic: author
Dynamic: author-email
Dynamic: classifier
Dynamic: description
Dynamic: description-content-type
Dynamic: home-page
Dynamic: license-file
Dynamic: requires-dist
Dynamic: requires-python
Dynamic: summary
